.travis.yml
README.rst
setup.py
docs/HISTORY.rst
docs/LICENSE
src/tarman/__init__.py
src/tarman/constants.py
src/tarman/containers.py
src/tarman/exceptions.py
src/tarman/helpers.py
src/tarman/overlaywin.py
src/tarman/tree.py
src/tarman/viewarea.py
src/tarman.egg-info/PKG-INFO
src/tarman.egg-info/SOURCES.txt
src/tarman.egg-info/dependency_links.txt
src/tarman.egg-info/entry_points.txt
src/tarman.egg-info/not-zip-safe
src/tarman.egg-info/requires.txt
src/tarman.egg-info/top_level.txt
src/tarman/tests/__init__.py
src/tarman/tests/test_containers.py
src/tarman/tests/test_helpers.py
src/tarman/tests/test_tree.py
src/tarman/tests/testdata/corrupted.tar
src/tarman/tests/testdata/testdata.tar.gz
src/tarman/tests/testdata/tešt.tar
src/tarman/tests/testdata/testdata/c
src/tarman/tests/testdata/testdata/a/ac
src/tarman/tests/testdata/testdata/a/aa/aaa
src/tarman/tests/testdata/testdata/a/ab/.git-keep
src/tarman/tests/testdata/testdata/b/ba/baa/baab
src/tarman/tests/testdata/testdata/b/ba/baa/baaa/baaaa