Metadata-Version: 1.1
Name: tarman
Version: 0.1.3
Summary: UNKNOWN
Home-page: https://github.com/matejc/tarman
Author: Matej Cotman
Author-email: cotman.matej@gmail.com
License: BSD
Keywords: tar zip archive curses
Platform: UNKNOWN
Classifier: Programming Language :: Python
Classifier: Environment :: Console :: Curses
Classifier: Topic :: System :: Archiving
